examples/__init__.py
examples/advanced_example.py
examples/graph_debugger_demo.py
examples/listener_example.py
examples/simple_example.py
examples/steel_man_demo.py
experiments/__init__.py
experiments/ambiguity_test.py
experiments/baseline_agent.py
experiments/benchmark.py
experiments/demo.py
experiments/generate_cost_curve.py
experiments/jailbreak_test.py
experiments/latent_state_scenario.py
experiments/mute_agent_experiment.py
experiments/run_extended_experiment.py
experiments/run_v2_experiments.py
experiments/run_v2_experiments_auto.py
experiments/visualize.py
experiments/v2_scenarios/__init__.py
experiments/v2_scenarios/scenario_1_deep_dependency.py
experiments/v2_scenarios/scenario_2_adversarial.py
experiments/v2_scenarios/scenario_3_false_positive.py
experiments/v2_scenarios/scenario_4_performance.py
mute_agent/__init__.py
mute_agent/core/__init__.py
mute_agent/core/execution_agent.py
mute_agent/core/handshake_protocol.py
mute_agent/core/reasoning_agent.py
mute_agent/knowledge_graph/__init__.py
mute_agent/knowledge_graph/graph_elements.py
mute_agent/knowledge_graph/multidimensional_graph.py
mute_agent/knowledge_graph/subgraph.py
mute_agent/listener/__init__.py
mute_agent/listener/listener.py
mute_agent/listener/state_observer.py
mute_agent/listener/threshold_config.py
mute_agent/listener/adapters/__init__.py
mute_agent/listener/adapters/base_adapter.py
mute_agent/listener/adapters/caas_adapter.py
mute_agent/listener/adapters/control_plane_adapter.py
mute_agent/listener/adapters/iatp_adapter.py
mute_agent/listener/adapters/scak_adapter.py
mute_agent/super_system/__init__.py
mute_agent/super_system/router.py
mute_agent/visualization/__init__.py
mute_agent/visualization/graph_debugger.py
mute_agent-0.3.0.dist-info/licenses/LICENSE
src/__init__.py
src/agents/__init__.py
src/agents/baseline_agent.py
src/agents/interactive_agent.py
src/agents/mute_agent.py
src/benchmarks/__init__.py
src/benchmarks/evaluator.py
src/core/__init__.py
src/core/mock_state.py
src/core/tools.py
mute_agent-0.3.0.dist-info/METADATA
mute_agent-0.3.0.dist-info/WHEEL
mute_agent-0.3.0.dist-info/top_level.txt
mute_agent-0.3.0.dist-info/RECORD
