Metadata-Version: 2.4
Name: mute-agent
Version: 0.3.0
Summary: Layer 5 Reference Implementation - Listener Agent with Dynamic Semantic Handshake Protocol
Home-page: https://github.com/imran-siddique/mute-agent
Author: Mute Agent Team
Classifier: Development Status :: 3 - Alpha
Classifier: Intended Audience :: Developers
Classifier: Topic :: Software Development :: Libraries :: Application Frameworks
Classifier: Programming Language :: Python :: 3
Classifier: Programming Language :: Python :: 3.8
Classifier: Programming Language :: Python :: 3.9
Classifier: Programming Language :: Python :: 3.10
Classifier: Programming Language :: Python :: 3.11
Classifier: Programming Language :: Python :: 3.12
Classifier: License :: OSI Approved :: MIT License
Classifier: Operating System :: OS Independent
Requires-Python: >=3.8
License-File: LICENSE
Provides-Extra: dev
Requires-Dist: pytest<9.0.0,>=7.0.0; extra == "dev"
Requires-Dist: pytest-cov<6.0.0,>=4.0.0; extra == "dev"
Requires-Dist: black<25.0.0,>=22.0.0; extra == "dev"
Requires-Dist: flake8<8.0.0,>=5.0.0; extra == "dev"
Requires-Dist: mypy<2.0.0,>=0.990; extra == "dev"
Provides-Extra: viz
Requires-Dist: matplotlib>=3.5.0; extra == "viz"
Requires-Dist: networkx>=2.6.0; extra == "viz"
Requires-Dist: pyvis>=0.3.0; extra == "viz"
Provides-Extra: full
Dynamic: author
Dynamic: classifier
Dynamic: description
Dynamic: description-content-type
Dynamic: home-page
Dynamic: license-file
Dynamic: provides-extra
Dynamic: requires-python
Dynamic: summary
